{
    "@class": "com.kony.gen.viz.model.container.KVizTabPane",
    "DNDConfig": null,
    "_activeTabsBackUp": [
        2
    ],
    "_height_": {
        "type": "string",
        "value": "100%"
    },
    "_left_": {
        "type": "string",
        "value": "0dp"
    },
    "_margin_": [
        0,
        0,
        0,
        0
    ],
    "_orientation_": 1,
    "_padding_": [
        0,
        0,
        0,
        0
    ],
    "_percent_": true,
    "_top_": {
        "type": "string",
        "value": "0dp"
    },
    "_width_": {
        "type": "string",
        "value": "100%"
    },
    "activefocusskin": "s570f91a4d174f38b613629509cf3de2",
    "activeskin": "sb775be58cec469c884797faad7d3e06",
    "activetab": 2,
    "activetabs": [
        0,
        1
    ],
    "allboxes": [],
    "android": {
        "psp": {
            "tabHeaderHeight": 10
        }
    },
    "canUpdateUI": true,
    "children": [
        "Tab1",
        "Tab2",
        "Tab3"
    ],
    "collapsedimage": "",
    "containerweight": 100,
    "disabledSkins": {},
    "expandedimage": "",
    "id": "MyTabPane001",
    "imageposition": "right",
    "inactiveskin": "s7f414401ecf42b9905ed28a48e0f462",
    "info": null,
    "iphone": {
        "psp": {
            "pageSkin": "s174ce876a7d4697b79da6670a68bad7",
            "progressIndicatorColor": "grey",
            "showProgressIndicator": true
        },
        "viewType": "tabview"
    },
    "iscustomlayout": false,
    "isvisible": true,
    "kuid": "ed684db64d3746059d3a95e7e00a2d48",
    "layouttype": 0,
    "margininpixel": false,
    "name": "kony.ui.TabPane",
    "paddinginpixel": false,
    "parent": "TestForm004",
    "pf": "TestForm004",
    "progressindicatorcolor": "grey",
    "retaincontentalignment": false,
    "retainflexpositionproperties": false,
    "screenlevelwidget": false,
    "showProgressIndicator": true,
    "swipeContext": {
        "currentPage": 0,
        "imageWidth": 0,
        "widthRatio": 0
    },
    "tabHeaderHeight": 10,
    "tabnamealignment": "left",
    "toggletabs": false,
    "viewconfig": {
        "collapsibleViewConfig": {
            "collapsedImage": "",
            "expandedImage": "",
            "imagePosition": "right",
            "tabNameAlignment": "left",
            "toggleTabs": false
        },
        "pageViewConfig": {
            "needPageIndicator": true,
            "pageOffDotImage": "pageoffdot.png",
            "pageOnDotImage": "pageondot.png"
        },
        "panoramaViewConfig": {
            "panoramaImage": "",
            "panoramaTitle": "",
            "panoramaTitleImage": ""
        },
        "tabViewConfig": {
            "headerPosition": "top",
            "image1": "tableftarrow.png",
            "image2": "tabrightarrow.png"
        }
    },
    "viewtype": "tabview",
    "wType": "TabPane",
    "zindex": 1
}